{"track_name":"Angst","album_name":"Introducing Brad Mehldau","recording_year":"1995","in_30_corpus":false,"bandleader":"Brad Mehldau","pianist":"Brad Mehldau","channel_overrides":{},"mbz_id":"d5546dce-f6fc-4cbb-8180-693234e60b8e","notes":"","time_signature":3,"first_downbeat":null,"rating_bass_audio":null,"rating_bass_detection":null,"rating_drums_audio":null,"rating_drums_detection":null,"rating_mix":null,"rating_piano_audio":null,"rating_piano_detection":null,"rating_comments":null,"has_annotations":false,"links":{"external":["https:\/\/www.youtube.com\/watch?v=z4Ta1Go8fjw"]},"excerpt_duration":"01:40","timestamps":{"start":"01:50","end":"03:30"},"log":[],"musicians":{"pianist":"Brad Mehldau","bassist":"Larry Grenadier","drummer":"Jorge Rossy","leader":"pianist"},"photos":{"musicians":{"pianist":null,"bassist":null,"drummer":null},"album_artwork":null},"fname":"mehldaub-angst-grenadierlrossyj-1995-d5546dce","tempo":195.1706418093,"validation":{"piano":null,"bass":null,"drums":null,"mix":null},"stem_silent_perc":{"piano":0.0118710511,"bass":0.0344521702,"drums":0.0}}