{"track_name":"Time on My Hands","album_name":"After Fajr","recording_year":"2004","pianist":"Ahmad Jamal","channel_overrides":{},"mbz_id":"5af058cd-4bc2-464a-8293-5823c91ec61b","notes":"","time_signature":4,"first_downbeat":7.42,"rating_bass_audio":null,"rating_bass_detection":null,"rating_drums_audio":null,"rating_drums_detection":null,"rating_mix":null,"rating_piano_audio":null,"rating_piano_detection":null,"rating_comments":null,"has_annotations":false,"links":{"external":["https:\/\/www.youtube.com\/watch?v=3V4S7AX3Zlw"]},"excerpt_duration":"01:18","timestamps":{"start":"02:22","end":"03:40"},"log":[],"musicians":{"pianist":"Ahmad Jamal","bassist":"James Cammack","drummer":"Idris Muhammad","leader":"pianist"},"photos":{"musicians":{"pianist":null,"bassist":null,"drummer":null},"album_artwork":null},"fname":"jamala-timeonmyhands-cammackjmuhammadi-2004-5af058cd"}