{"track_name":"The Balanced Scales","album_name":"Flanagans Shenanigans","recording_year":"1993","pianist":"Tommy Flanagan","channel_overrides":{},"mbz_id":"c5831559-f3ea-4000-9e0a-ce38d3f90bac","notes":"ballad switches to double time","time_signature":4,"first_downbeat":7.4,"rating_bass_audio":null,"rating_bass_detection":null,"rating_drums_audio":null,"rating_drums_detection":null,"rating_mix":null,"rating_piano_audio":null,"rating_piano_detection":null,"rating_comments":null,"has_annotations":false,"links":{"external":["https:\/\/www.youtube.com\/watch?v=OHmV9yzLaDQ"]},"excerpt_duration":"02:00","timestamps":{"start":"03:30","end":"05:30"},"log":[],"musicians":{"pianist":"Tommy Flanagan","bassist":"Jesper Lundgaard","drummer":"Lewis Nash","leader":"pianist"},"photos":{"musicians":{"pianist":null,"bassist":null,"drummer":null},"album_artwork":null},"fname":"flanagant-thebalancedscales-lundgaardjnashl-1993-c5831559"}