{"track_name":"Lets","album_name":"Flanagans Shenanigans","recording_year":"1993","pianist":"Tommy Flanagan","channel_overrides":{},"mbz_id":"8efcf3b9-b019-4fd1-8f30-4aa1b57f8348","notes":"","time_signature":4,"first_downbeat":10.8,"rating_bass_audio":null,"rating_bass_detection":null,"rating_drums_audio":null,"rating_drums_detection":null,"rating_mix":null,"rating_piano_audio":null,"rating_piano_detection":null,"rating_comments":null,"has_annotations":false,"links":{"external":["https:\/\/www.youtube.com\/watch?v=FNhU8VpCowI"]},"excerpt_duration":"01:54","timestamps":{"start":"00:32","end":"02:26"},"log":[],"musicians":{"pianist":"Tommy Flanagan","bassist":"Jesper Lundgaard","drummer":"Lewis Nash","leader":"pianist"},"photos":{"musicians":{"pianist":null,"bassist":null,"drummer":null},"album_artwork":null},"fname":"flanagant-lets-lundgaardjnashl-1993-8efcf3b9"}