{"track_name":"California Here I Come","album_name":"California Here I Come","recording_year":"1967","pianist":"Bill Evans","channel_overrides":{"bass":"l"},"mbz_id":"fc6dbef4-7b91-49ee-b003-acca01d833ff","notes":"","time_signature":4,"first_downbeat":15.16,"rating_bass_audio":null,"rating_bass_detection":null,"rating_drums_audio":null,"rating_drums_detection":null,"rating_mix":null,"rating_piano_audio":null,"rating_piano_detection":null,"rating_comments":null,"has_annotations":false,"links":{"external":["https:\/\/www.youtube.com\/watch?v=5snGcdGh86Q"]},"excerpt_duration":"01:23","timestamps":{"start":"01:37","end":"03:00"},"log":[],"musicians":{"pianist":"Bill Evans","bassist":"Eddie Gomez","drummer":"Philly Joe Jones","leader":"pianist"},"photos":{"musicians":{"pianist":null,"bassist":null,"drummer":null},"album_artwork":null},"fname":"evansb-californiahereicome-gomezejoep-1967-fc6dbef4"}