{"track_name":"My Romance","album_name":"Turn Out the Stars The Final Village Vanguard Sessions","recording_year":"1980","in_30_corpus":false,"bandleader":"Bill Evans","pianist":"Bill Evans","channel_overrides":{},"mbz_id":"607b3caf-50a4-4a0d-a065-06a70c8db810","notes":"","time_signature":4,"first_downbeat":6.69,"rating_bass_audio":3.0,"rating_bass_detection":3.0,"rating_drums_audio":3.0,"rating_drums_detection":3.0,"rating_mix":3.0,"rating_piano_audio":3.0,"rating_piano_detection":3.0,"rating_comments":null,"has_annotations":false,"links":{"external":["https:\/\/www.youtube.com\/watch?v=V6vFgzw0KmM"]},"excerpt_duration":"00:32","timestamps":{"start":"05:30","end":"06:02"},"log":[],"musicians":{"pianist":"Bill Evans","bassist":"Marc Johnson","drummer":"Joe LaBarbera","leader":"pianist"},"photos":{"musicians":{"pianist":null,"bassist":null,"drummer":null},"album_artwork":null},"fname":"evansb-myromance-johnsonmlabarberaj-1980-607b3caf","tempo":226.4341546393,"validation":{"piano":null,"bass":null,"drums":null,"mix":null},"stem_silent_perc":{"piano":0.0024189482,"bass":0.0,"drums":0.0}}