{"track_name":"Well You Neednt","album_name":"The Perfect Set","recording_year":"1996","in_30_corpus":true,"bandleader":"Kenny Barron","pianist":"Kenny Barron","channel_overrides":{},"mbz_id":"fbe7467b-27b4-4bbe-8c7f-4b5b9fa1e9b0","notes":"","time_signature":4,"first_downbeat":10.98,"rating_bass_audio":null,"rating_bass_detection":null,"rating_drums_audio":null,"rating_drums_detection":null,"rating_mix":null,"rating_piano_audio":null,"rating_piano_detection":null,"rating_comments":null,"has_annotations":false,"links":{"external":["https:\/\/www.youtube.com\/watch?v=O67aNJSufUM"]},"excerpt_duration":"06:51","timestamps":{"start":"00:29","end":"07:20"},"log":[],"musicians":{"pianist":"Kenny Barron","bassist":"Ray Drummond","drummer":"Ben Riley","leader":"pianist"},"photos":{"musicians":{"pianist":null,"bassist":null,"drummer":null},"album_artwork":null},"fname":"barronk-wellyouneednt-drummondrrileyb-1996-fbe7467b","tempo":259.7314334604,"validation":{"piano":null,"bass":null,"drums":null,"mix":null},"stem_silent_perc":{"piano":0.0,"bass":0.1008625227,"drums":0.0}}