{"track_name":"Rain Check","album_name":"Ahmad Jamal Eight Classic Albums","recording_year":"1960","in_30_corpus":true,"bandleader":"Ahmad Jamal","pianist":"Ahmad Jamal","channel_overrides":{"bass":"l","piano":"r","drums":"r"},"mbz_id":"30cd5578-e1c2-4ed2-83bb-b9a613daf53b","notes":"","time_signature":4,"first_downbeat":17.95,"rating_bass_audio":null,"rating_bass_detection":null,"rating_drums_audio":null,"rating_drums_detection":null,"rating_mix":null,"rating_piano_audio":null,"rating_piano_detection":null,"rating_comments":null,"has_annotations":false,"links":{"external":["https:\/\/www.youtube.com\/watch?v=M532GR-5u8M"]},"excerpt_duration":"03:16","timestamps":{"start":"00:52","end":"04:08"},"log":[],"musicians":{"pianist":"Ahmad Jamal","bassist":"Israel Crosby","drummer":"Vernell Fournier","leader":"pianist"},"photos":{"musicians":{"pianist":null,"bassist":null,"drummer":null},"album_artwork":null},"fname":"jamala-raincheck-crosbyifournierv-1960-30cd5578","tempo":185.1886854789,"validation":{"piano":null,"bass":null,"drums":null,"mix":null},"stem_silent_perc":{"piano":0.2468056987,"bass":0.9820234369,"drums":0.0}}