{"track_name":"There Is No Greater Love","album_name":"Green Chimneys","recording_year":"1984","in_30_corpus":true,"bandleader":"Kenny Barron","pianist":"Kenny Barron","channel_overrides":{"piano":"r","bass":"l","drums":"l"},"mbz_id":"90d41f7e-b674-4059-b72c-d2928db3de0c","notes":"","time_signature":4,"first_downbeat":7.17,"rating_bass_audio":null,"rating_bass_detection":null,"rating_drums_audio":null,"rating_drums_detection":null,"rating_mix":null,"rating_piano_audio":null,"rating_piano_detection":null,"rating_comments":null,"has_annotations":false,"links":{"external":["https:\/\/www.youtube.com\/watch?v=SGQWwc1Xypo"]},"excerpt_duration":"04:12","timestamps":{"start":"01:28","end":"05:40"},"log":[],"musicians":{"pianist":"Kenny Barron","bassist":"Buster Williams","drummer":"Ben Riley","leader":"pianist"},"photos":{"musicians":{"pianist":null,"bassist":null,"drummer":null},"album_artwork":null},"fname":"barronk-thereisnogreaterlove-williamsbrileyb-1984-90d41f7e","tempo":210.5505946556,"validation":{"piano":null,"bass":null,"drums":null,"mix":null},"stem_silent_perc":{"piano":0.0,"bass":0.1039098649,"drums":0.0}}