{"track_name":"A Stranger in Paradise","album_name":"If You Could See Me Now","recording_year":"1974","in_30_corpus":false,"bandleader":"Kenny Drew","pianist":"Kenny Drew","channel_overrides":{},"mbz_id":"d131cfe3-6c01-4611-9933-1bb21b01eb54","notes":"","time_signature":4,"first_downbeat":null,"rating_bass_audio":null,"rating_bass_detection":null,"rating_drums_audio":null,"rating_drums_detection":null,"rating_mix":null,"rating_piano_audio":null,"rating_piano_detection":null,"rating_comments":null,"has_annotations":false,"links":{"external":["https:\/\/www.youtube.com\/watch?v=oZWAGXW0NUE"]},"excerpt_duration":"02:07","timestamps":{"start":"01:38","end":"03:45"},"log":[],"musicians":{"pianist":"Kenny Drew","bassist":"Niels-Henning \u00d8rsted Pedersen","drummer":"Albert \u201cTootie\u201d Heath","leader":"pianist"},"photos":{"musicians":{"pianist":null,"bassist":null,"drummer":null},"album_artwork":null},"fname":"drewk-astrangerinparadise-rstedntootiea-1974-d131cfe3","tempo":226.7168350014,"validation":{"piano":null,"bass":null,"drums":null,"mix":null},"stem_silent_perc":{"piano":1.110223025e-16,"bass":0.0022854041,"drums":0.0}}